ibstract/__init__.py
ibstract/brokers.py
ibstract/financedata.py
ibstract/ibglobals.py
ibstract/marketdata.py
ibstract/nyse_dates.csv
ibstract/trading.py
ibstract/utils.py
ibstract-1.0.0a2.dist-info/DESCRIPTION.rst
ibstract-1.0.0a2.dist-info/METADATA
ibstract-1.0.0a2.dist-info/RECORD
ibstract-1.0.0a2.dist-info/WHEEL
ibstract-1.0.0a2.dist-info/metadata.json
ibstract-1.0.0a2.dist-info/top_level.txt
