Metadata-Version: 2.0
Name: ibstract
Version: 1.0.0a2
Summary: Asynchronous financial trading data management
Home-page: https://github.com/jesseliu0/ibstract
Author: Jesse Liu
Author-email: jesseliu0@gmail.com
License: MIT
Download-URL: https://pypi.python.org/pypi/ibstract
Keywords: ibapi asyncio interactive brokers async algorithmicquantitative trading finance
Platform: POSIX
Classifier: License :: OSI Approved :: MIT License
Classifier: Intended Audience :: Developers
Classifier: Intended Audience :: Financial and Insurance Industry
Classifier: Programming Language :: Python :: 3
Classifier: Programming Language :: Python :: 3.6
Classifier: Operating System :: POSIX
Classifier: Environment :: Web Environment
Classifier: Development Status :: 3 - Alpha
Classifier: Topic :: Office/Business :: Financial :: Investment
Classifier: Topic :: Scientific/Engineering
Requires-Python: >=3.6.0
Requires-Dist: SQLAlchemy (>=1.1.9)
Requires-Dist: aiomysql (>=0.0.9)
Requires-Dist: ib-insync (>=0.8.5)
Requires-Dist: pandas (>=0.20.1)
Requires-Dist: tzlocal (>=1.4)
